sim/11-behavioral-brown/shifter.sv
module shifter (W, Shift, Y , k); //figure4.54.v
	input [3:0] W;
	input Shift;
	output reg [3:0] Y;
	output reg k;
	
	always @(W, Shift)
	begin
		if (Shift)
		begin
			Y = W >> 1;
			k = W[0];
		end
		else
		begin
			Y = W;
			k = 0;
		end
	end

endmodule

sim/11-behavioral-brown/compare.sv
module compare (A, B, AeqB, AgtB, AltB); //figure4.40.v
	input [3:0] A, B;
	output reg AeqB, AgtB, AltB;
		
	always @(A, B)
	begin
		AeqB = 0;
		AgtB = 0;
		AltB = 0;
		if(A == B)
			AeqB = 1;
		else if (A > B)
			AgtB = 1;
		else
			AltB = 1;
	end
				
endmodule

sim/11-behavioral-brown/dec2to4.sv
module dec2to4 (W, En, Y); // figure4.32.v
	input [1:0] W;
	input En;
	output reg [0:3] Y;
	
	always @(W, En)
	begin
		if (En == 0)
			Y = 4'b0000;
		else
			case (W)
				0: Y = 4'b1000;
				1: Y = 4'b0100;
				2: Y = 4'b0010;
				3: Y = 4'b0001;
			endcase
	end
endmodule

sim/11-behavioral-brown/comparator.sv
module comparator (X, Y, V, N, Z); // figure3.47.v
	parameter n = 32;
	input [n-1:0] X, Y; 
	output reg V, N, Z; 
	reg [n-1:0] S; 
	reg [n:0] C;
	integer k;

	always @(X, Y)
	begin
		C[0] = 1'b1;
		for (k = 0; k < n;  k = k + 1)
		begin
			S[k] = X[k] ^ ~Y[k] ^ C[k];
			C[k+1] = (X[k] & ~Y[k]) | (X[k] & C[k]) | (~Y[k] & C[k]);
		end
		V  = C[n] ^ C[n-1]; 
		N = S[n-1]; 
		Z = !S;
	end

endmodule

sim/11-behavioral-brown/addern.sv
module addern (carryin, X, Y, S, carryout, overflow); // figure3.28.v
	parameter n = 32;
	input carryin;
	input [n-1:0] X, Y;
	output reg [n-1:0] S;
	output reg carryout, overflow;
	reg [n:0] Sum;

	always @(X, Y, carryin)
	begin
		Sum = {1'b0, X} + {1'b0, Y} + carryin;
		S = Sum[n-1:0];
		carryout = Sum[n];
		overflow = (X[n-1] & Y[n-1] & ~S[n-1]) | 
		           (~X[n-1] & ~Y[n-1] & S[n-1]);
	end
endmodule

sim/09-priority-encoder/priority_encoder.sv
module priority_encoder (
  input [3:0] W,
  output reg [1:0] Y,
  output reg Z);

  always @(W) 
  begin
  	Z = 1; 
    casex (W)
	  4'b1xxx: Y = 3; 
      4'b01xx: Y = 2; 
      4'b001x: Y = 1; 
      4'b0001: Y = 0; 
      default:
	    begin
	      Z = 0;
        Y = 2'bx; 
      end
	  endcase 
  end
endmodule

sim/11-behavioral-brown/mux4to1.sv
module mux4to1 (W, S, f); // figure4.28.v
	input [0:3] W;
	input [1:0] S;
	output reg f;
		
	always @(W, S)
		if (S == 0)
			f = W[0];
		else if (S == 1)
			f = W[1];
		else if (S == 2)
			f = W[2];
		else if (S == 3)
			f = W[3];
endmodule

sim/11-behavioral-brown/top.sv
module top (
  input [31:0] random_bits,
  output mux4to1_out,
  output [1:0] mux8to2_out,
  output [1:0] priority_encoder_Y_out,
  output priority_encoder_Z_out,
  output [7:0] addern_S_out,
	output addern_carryout_out, addern_overflow_out,
  output comparator_V_out, comparator_N_out, comparator_Z_out,
  output [0:3] dec2to4_Y_out,
  output compareAeqB, compareAgtB, compareAltB,
  output [3:0] shifter_Y_out,
  output shifter_k_out);

  mux4to1 mux4to1_ (
    .W(random_bits[3:0]),
    .S(random_bits[5:4]),
    .f(mux4to1_out)
  );

  mux8to2 mux_ (
    .W(random_bits[7:0]),
    .S(random_bits[9:8]),
    .f(mux8to2_out)
  );
  
  priority_encoder pe_ (
    .W(random_bits[11:8]),
    .Y(priority_encoder_Y_out),
    .Z(priority_encoder_Z_out)
  );

  addern #(8) adder_ (
    .carryin(random_bits[16]),
    .X(random_bits[ 7:0]),
    .Y(random_bits[15:8]),
    .S(addern_S_out),
    .carryout(addern_carryout_out),
    .overflow(addern_overflow_out)
  );

comparator #(3) comp_ (
  .X(random_bits[19:17]),
  .Y(random_bits[22:20]),
  .V(comparator_V_out),
  .N(comparator_N_out),
  .Z(comparator_Z_out)
  );

dec2to4 dec2to4_ (
  .En(random_bits[24]),
  .W(random_bits[26:25]),
  .Y(dec2to4_Y_out)
);

compare cmp_ (
  .A(random_bits[3:0]),
  .B(random_bits[17:14]),
  .AeqB(compareAeqB),
  .AgtB(compareAgtB),
  .AltB(compareAltB)
);

shifter shifter_ (
  .W(random_bits[31:28]),
  .Shift(random_bits[16]),
  .Y(shifter_Y_out),
  .k(shifter_k_out)
);

endmodule

sim/09-priority-encoder/tests/test.sv
// Testbench
module test;

  logic clk, Z, Z_expected;
  logic [15:0] W;
  logic [3:0] Y, Y_expected;

  logic [31:0] vectornum, errors;
  logic [31:0] testvectors [0:41];
  
  // Instantiate design under test
  top dut (W, Y, Z);
  
  // generate clock
  always begin
    clk = 0; #50; clk = 1; #50;
  end
  
    // at start of test, load vectors
  initial begin
    $readmemb("values.tv", testvectors);
    vectornum = 0; errors = 0;
  end
  
    // apply test vectors at rising edge of clock
  always @(posedge clk)
    begin
      W = testvectors[vectornum][20:5];
      Y_expected = testvectors[vectornum][4:1];
      Z_expected = testvectors[vectornum][0];
      display;
    end
  
  initial begin
    // Dump waves
    $dumpfile("dump.vcd");
    $dumpvars;
  end

 // check results on falling edge of clock
 always @(negedge clk) 
   begin
     if (Y !== Y_expected || Z !== Z_expected) begin
       $display("Error in vector %0d", vectornum);
       $display(" Input : W = %b", W);
       $display("  Output: Y = %b (%b expected)", Y, Y_expected); 
       $display("    Output: Z = %b (%b expected)", Z, Z_expected); 
       errors = errors+1;
     end
     vectornum = vectornum + 1;
     if (testvectors[vectornum][0] === 1'bx) begin
       $display("%d tests completed with %d errors", vectornum, errors);
       $finish;
     end
   end  
  
  task display;
    #1 $display("W=%16b => Y=%4b Z=%b", W, Y, Z);
  endtask

endmodule

sim/09-priority-encoder/mux8to2.sv
module mux8to2 (W, S, f); 
  input [7:0] W;
  input [1:0] S;
  output reg [1:0] f;

  always @(W, S) 
    case (S)
      0: f = W[1:0];
      1: f = W[3:2];
      2: f = W[5:4];
      3: f = W[7:6];
    endcase
endmodule

sim/11-behavioral-brown/tests/dump.vcd
$date
	Fri Jun 13 14:54:04 2025
$end
$version
	Icarus Verilog
$end
$timescale
	1s
$end
$scope module mux8to2 $end
$var wire 2 ! S [1:0] $end
$var wire 8 " W [7:0] $end
$var reg 2 # f [1:0] $end
$upscope $end
$scope module priority_encoder $end
$var wire 4 $ W [3:0] $end
$var reg 2 % Y [1:0] $end
$var reg 1 & Z $end
$upscope $end
$scope module test $end
$var wire 4 ' Y [3:0] $end
$var wire 1 ( Z $end
$var reg 16 ) W [15:0] $end
$var reg 4 * Y_expected [3:0] $end
$var reg 1 + Z_expected $end
$var reg 1 , clk $end
$var reg 32 - errors [31:0] $end
$var reg 32 . vectornum [31:0] $end
$scope module dut $end
$var wire 16 / W [15:0] $end
$var wire 4 0 Y [3:0] $end
$var wire 1 ( Z $end
$upscope $end
$scope task display $end
$upscope $end
$upscope $end
$enddefinitions $end
$comment Show the parameter values. $end
$dumpall
$end
#0
$dumpvars
bz 0
bx /
b0 .
b0 -
0,
x+
bx *
bx )
z(
bz '
1&
b11 %
bz $
bx #
bz "
bz !
$end
#50
0+
b0 )
b0 /
1,
#100
b1 .
b1 -
0,
#150
1+
b0 *
b1 )
b1 /
1,
#200
b10 .
b10 -
0,
#250
b1 *
b10 )
b10 /
1,
#300
b11 .
b11 -
0,
#350
b10 *
b100 )
b100 /
1,
#400
b100 .
b100 -
0,
#450
b11 *
b1000 )
b1000 /
1,
#500
b101 .
b101 -
0,
#550
b100 *
b10000 )
b10000 /
1,
#600
b110 .
b110 -
0,
#650
b101 *
b100000 )
b100000 /
1,
#700
b111 .
b111 -
0,
#750
b110 *
b1000000 )
b1000000 /
1,
#800
b1000 .
b1000 -
0,
#850
b111 *
b10000000 )
b10000000 /
1,
#900
b1001 .
b1001 -
0,
#950
b1000 *
b100000000 )
b100000000 /
1,
#1000
b1010 .
b1010 -
0,
#1050
b1001 *
b1000000000 )
b1000000000 /
1,
#1100
b1011 .
b1011 -
0,
#1150
b1010 *
b10000000000 )
b10000000000 /
1,
#1200
b1100 .
b1100 -
0,
#1250
b1011 *
b100000000000 )
b100000000000 /
1,
#1300
b1101 .
b1101 -
0,
#1350
b1100 *
b1000000000000 )
b1000000000000 /
1,
#1400
b1110 .
b1110 -
0,
#1450
b1101 *
b10000000000000 )
b10000000000000 /
1,
#1500
b1111 .
b1111 -
0,
#1550
b1110 *
b100000000000000 )
b100000000000000 /
1,
#1600
b10000 .
b10000 -
0,
#1650
b1111 *
b1000000000000000 )
b1000000000000000 /
1,
#1700
b10001 .
b10001 -
0,
#1750
b1100000000000000 )
b1100000000000000 /
1,
#1800
b10010 .
b10010 -
0,
#1850
b1110000000000000 )
b1110000000000000 /
1,
#1900
b10011 .
b10011 -
0,
#1950
b1111000000000000 )
b1111000000000000 /
1,
#2000
b10100 .
b10100 -
0,
#2050
b1111110000000000 )
b1111110000000000 /
1,
#2100
b10101 .
b10101 -
0,
#2150
b1111111100000000 )
b1111111100000000 /
1,
#2200
b10110 .
b10110 -
0,
#2250
b1111111111000000 )
b1111111111000000 /
1,
#2300
b10111 .
b10111 -
0,
#2350
b1111111111110000 )
b1111111111110000 /
1,
#2400
b11000 .
b11000 -
0,
#2450
b1111111111111100 )
b1111111111111100 /
1,
#2500
b11001 .
b11001 -
0,
#2550
b1111111111111111 )
b1111111111111111 /
1,
#2600
b11010 .
b11010 -
0,
#2650
b1110 *
b111000000000000 )
b111000000000000 /
1,
#2700
b11011 .
b11011 -
0,
#2750
b111110000100100 )
b111110000100100 /
1,
#2800
b11100 .
b11100 -
0,
#2850
b1101 *
b11111000000110 )
b11111000000110 /
1,
#2900
b11101 .
b11101 -
0,
#2950
b1100 *
b1110000100110 )
b1110000100110 /
1,
#3000
b11110 .
b11110 -
0,
#3050
b1011 *
b100000011100 )
b100000011100 /
1,
#3100
b11111 .
b11111 -
0,
#3150
b1010 *
b10110011000 )
b10110011000 /
1,
#3200
b100000 .
b100000 -
0,
#3250
b1001 *
b1111110000 )
b1111110000 /
1,
#3300
b100001 .
b100001 -
0,
#3350
b1000 *
b111101010 )
b111101010 /
1,
#3400
b100010 .
b100010 -
0,
#3450
b111 *
b11110000 )
b11110000 /
1,
#3500
b100011 .
b100011 -
0,
#3550
b110 *
b1011111 )
b1011111 /
1,
#3600
b100100 .
b100100 -
0,
#3650
b101 *
b101010 )
b101010 /
1,
#3700
b100101 .
b100101 -
0,
#3750
b100 *
b10101 )
b10101 /
1,
#3800
b100110 .
b100110 -
0,
#3850
b11 *
b1010 )
b1010 /
1,
#3900
b100111 .
b100111 -
0,
#3950
b10 *
b101 )
b101 /
1,
#4000
b101000 .
b101000 -
0,
#4050
b1 *
b11 )
b11 /
1,
#4100
b101001 .
b101001 -
0,
#4150
b0 *
b1 )
b1 /
1,
#4200
b101010 .
b101010 -
0,
